[
    {
        "name": "休闲游戏.html",
        "icon": "",
        "type": "file"
    },
    {
        "name": "全部游戏.html",
        "icon": "",
        "type": "file"
    },
    {
        "name": "动作游戏.html",
        "icon": "",
        "type": "file"
    },
    {
        "name": "大型游戏.html",
        "icon": "",
        "type": "file"
    },
    {
        "name": "射击游戏.html",
        "icon": "",
        "type": "file"
    },
    {
        "name": "手机游戏.html",
        "icon": "",
        "type": "file"
    },
    {
        "name": "棋牌游戏.html",
        "icon": "",
        "type": "file"
    },
    {
        "name": "消除游戏.html",
        "icon": "",
        "type": "file"
    },
    {
        "name": "益智游戏.html",
        "icon": "",
        "type": "file"
    },
    {
        "name": "策略游戏.html",
        "icon": "",
        "type": "file"
    }
]